{"cameraMode":{"drawMode":0,"name":"Shaded","section":"Shading Mode"},"sceneLighting":true,"audioPlay":false,"sceneViewState":{"m_AlwaysRefresh":false,"showFog":true,"showSkybox":true,"showFlares":true,"showImageEffects":true,"showParticleSystems":true,"showVisualEffectGraphs":true,"m_FxEnabled":true},"in2DMode":false,"pivot":{"x":2.496710777282715,"y":-5.5908308029174809,"z":-23.742000579833986},"rotation":{"x":0.05849422886967659,"y":0.9396106600761414,"z":-0.267342209815979,"w":0.2055758237838745},"size":10.67281723022461,"orthographic":false}